{
  "generatedAt": "2026-04-02T04:38:25.886Z",
  "window": "7d",
  "source": "ga4",
  "items": [
    {
      "slug": "incredibox",
      "score": 10246
    },
    {
      "slug": "cuphead",
      "score": 299
    },
    {
      "slug": "sprunki-phase-8",
      "score": 241
    },
    {
      "slug": "incredibox-dystopia",
      "score": 162
    },
    {
      "slug": "sprunki-clicker",
      "score": 145
    },
    {
      "slug": "steal-a-brainrot",
      "score": 140
    },
    {
      "slug": "fiddlebops-fix",
      "score": 132
    },
    {
      "slug": "incredibox-yellow-colorbox",
      "score": 118
    },
    {
      "slug": "incredibox-choir",
      "score": 117
    },
    {
      "slug": "baldis-basics",
      "score": 113
    },
    {
      "slug": "incredibox-xrun-simulator",
      "score": 93
    },
    {
      "slug": "99-nights-in-the-forest",
      "score": 86
    },
    {
      "slug": "incredibox-downtown-simulator",
      "score": 85
    },
    {
      "slug": "level-devil",
      "score": 80
    },
    {
      "slug": "geometry-dash",
      "score": 72
    },
    {
      "slug": "grow-a-garden",
      "score": 69
    },
    {
      "slug": "incredibox-vibin",
      "score": 68
    },
    {
      "slug": "elastic-man",
      "score": 66
    },
    {
      "slug": "whack-your-boss",
      "score": 66
    },
    {
      "slug": "choir",
      "score": 56
    },
    {
      "slug": "sprunki-mustard",
      "score": 56
    },
    {
      "slug": "super-smash-flash-2-v08",
      "score": 56
    },
    {
      "slug": "minecraft",
      "score": 55
    },
    {
      "slug": "fiddlebops-but-sprunki",
      "score": 51
    },
    {
      "slug": "60s-burger-run",
      "score": 50
    },
    {
      "slug": "incredibox-carol-of-the-bells",
      "score": 50
    },
    {
      "slug": "fiddlebops-but-dandys-world",
      "score": 42
    },
    {
      "slug": "friday-night-funkin",
      "score": 42
    },
    {
      "slug": "happy-wheels",
      "score": 42
    },
    {
      "slug": "geometry-dash-wave",
      "score": 41
    },
    {
      "slug": "murder",
      "score": 40
    },
    {
      "slug": "incredibox-trillybox",
      "score": 38
    },
    {
      "slug": "fiddlebops-sprunki",
      "score": 33
    },
    {
      "slug": "incredibox-cool-as-ice",
      "score": 32
    },
    {
      "slug": "cat-mario",
      "score": 30
    },
    {
      "slug": "geometry-dash-meltdown",
      "score": 28
    },
    {
      "slug": "google-doodle-baseball",
      "score": 28
    },
    {
      "slug": "incredibox-geek-dance-simulator",
      "score": 26
    },
    {
      "slug": "dumb-ways-to-die",
      "score": 25
    },
    {
      "slug": "incredibox-beatnik-simulator",
      "score": 25
    },
    {
      "slug": "tunnel-rush",
      "score": 25
    },
    {
      "slug": "incredibox-melophobia",
      "score": 22
    },
    {
      "slug": "crossyroad",
      "score": 21
    },
    {
      "slug": "sprunki-good-night",
      "score": 21
    },
    {
      "slug": "incredibox-banana",
      "score": 20
    },
    {
      "slug": "slippery-slope",
      "score": 18
    },
    {
      "slug": "stick-fighter",
      "score": 18
    },
    {
      "slug": "fiddlebops-sprunkbop",
      "score": 15
    },
    {
      "slug": "pikmin-no-sprunki",
      "score": 14
    },
    {
      "slug": "basket-random",
      "score": 12
    },
    {
      "slug": "incredibox-yaboo",
      "score": 12
    },
    {
      "slug": "ragdoll-archers",
      "score": 12
    },
    {
      "slug": "geometry-dash-subzero",
      "score": 11
    },
    {
      "slug": "fiddlebops-polos",
      "score": 10
    },
    {
      "slug": "ovo",
      "score": 10
    },
    {
      "slug": "cookie-clicker-2",
      "score": 9
    },
    {
      "slug": "sprunkgerny",
      "score": 9
    },
    {
      "slug": "stick-war",
      "score": 9
    },
    {
      "slug": "fiddlebops-sprunksters-remix",
      "score": 8
    },
    {
      "slug": "he-likes-the-darkness",
      "score": 8
    },
    {
      "slug": "ovo-dimensions",
      "score": 8
    },
    {
      "slug": "super-smash-flash-2-v09",
      "score": 8
    },
    {
      "slug": "incredibox-riser",
      "score": 7
    },
    {
      "slug": "incredibox-sprunksters",
      "score": 7
    },
    {
      "slug": "sprunki-babies",
      "score": 7
    },
    {
      "slug": "bloons-td-6",
      "score": 6
    },
    {
      "slug": "incredibox-hijinks",
      "score": 6
    },
    {
      "slug": "incredibox-piege-simulator",
      "score": 6
    },
    {
      "slug": "incredibox-studio",
      "score": 6
    },
    {
      "slug": "sprunki-phase-1",
      "score": 6
    },
    {
      "slug": "cluster-rush",
      "score": 5
    },
    {
      "slug": "google-snake",
      "score": 5
    },
    {
      "slug": "incredibox-instrumentalist",
      "score": 5
    },
    {
      "slug": "incredibox-sprinkle",
      "score": 5
    },
    {
      "slug": "paper-minecraft",
      "score": 5
    },
    {
      "slug": "sprunki-mod-BFDI",
      "score": 5
    },
    {
      "slug": "superhot",
      "score": 5
    },
    {
      "slug": "3d-free-kick",
      "score": 4
    },
    {
      "slug": "fly-or-die",
      "score": 4
    },
    {
      "slug": "gladihoppers",
      "score": 4
    },
    {
      "slug": "incredibox-creatophobos",
      "score": 4
    },
    {
      "slug": "incredibox-donki-abgerny",
      "score": 4
    },
    {
      "slug": "incredibox-kochari",
      "score": 4
    },
    {
      "slug": "sprunki-craft",
      "score": 4
    },
    {
      "slug": "bad-time-simulator",
      "score": 3
    },
    {
      "slug": "bricks-breaker",
      "score": 3
    },
    {
      "slug": "bullet-force",
      "score": 3
    },
    {
      "slug": "drift-hunters",
      "score": 3
    },
    {
      "slug": "fruit-slot-machine",
      "score": 3
    },
    {
      "slug": "geometry-dash-lite",
      "score": 3
    },
    {
      "slug": "incredibox-wolfgang",
      "score": 3
    },
    {
      "slug": "iron-snout",
      "score": 3
    },
    {
      "slug": "kingdom-rush-frontiers",
      "score": 3
    },
    {
      "slug": "pokemon-emerald",
      "score": 3
    },
    {
      "slug": "rocket-league",
      "score": 3
    },
    {
      "slug": "sprunki-retake-new-human",
      "score": 3
    },
    {
      "slug": "sprunki-squid-remix",
      "score": 3
    },
    {
      "slug": "sprunki-virus-new-update",
      "score": 3
    },
    {
      "slug": "the-binding-of-isaac",
      "score": 3
    },
    {
      "slug": "thief-puzzle",
      "score": 3
    },
    {
      "slug": "trap-the-cat",
      "score": 3
    },
    {
      "slug": "war-of-sticks",
      "score": 3
    },
    {
      "slug": "yojou-sprunki-mustard",
      "score": 3
    },
    {
      "slug": "addiction-mini",
      "score": 2
    },
    {
      "slug": "aloha-mahjong",
      "score": 2
    },
    {
      "slug": "bloons-td-5",
      "score": 2
    },
    {
      "slug": "capybara-clicker",
      "score": 2
    },
    {
      "slug": "cricket-mania",
      "score": 2
    },
    {
      "slug": "crossword",
      "score": 2
    },
    {
      "slug": "diner-dash",
      "score": 2
    },
    {
      "slug": "drifting-mania",
      "score": 2
    },
    {
      "slug": "endless-truck",
      "score": 2
    },
    {
      "slug": "fancy-pants",
      "score": 2
    },
    {
      "slug": "fancy-pants-3",
      "score": 2
    },
    {
      "slug": "five-nights-at-freddy-1",
      "score": 2
    },
    {
      "slug": "five-nights-at-freddy-4",
      "score": 2
    },
    {
      "slug": "five-nights-at-freddy-sl",
      "score": 2
    },
    {
      "slug": "g-switch",
      "score": 2
    },
    {
      "slug": "getting-over-it",
      "score": 2
    },
    {
      "slug": "incredibox-rave",
      "score": 2
    },
    {
      "slug": "infiltrating-the-airship",
      "score": 2
    },
    {
      "slug": "jurassic-run",
      "score": 2
    },
    {
      "slug": "minesweeper-1000",
      "score": 2
    },
    {
      "slug": "only-up",
      "score": 2
    },
    {
      "slug": "retro-bowl",
      "score": 2
    },
    {
      "slug": "slope-3",
      "score": 2
    },
    {
      "slug": "sprunki-abgerny",
      "score": 2
    },
    {
      "slug": "sprunki-phase-2-5",
      "score": 2
    },
    {
      "slug": "sprunki-phase-5",
      "score": 2
    },
    {
      "slug": "sprunki-pyramixed",
      "score": 2
    },
    {
      "slug": "sprunki-retake",
      "score": 2
    },
    {
      "slug": "sprunki-retake-bonus-characters",
      "score": 2
    },
    {
      "slug": "sprunki-rotrizi-5",
      "score": 2
    },
    {
      "slug": "sprunki-sonic",
      "score": 2
    },
    {
      "slug": "sprunki-swapped-horror",
      "score": 2
    },
    {
      "slug": "super-smash-flash",
      "score": 2
    },
    {
      "slug": "the-haze-pixelbox",
      "score": 2
    },
    {
      "slug": "there-is-no-game",
      "score": 2
    },
    {
      "slug": "tomb-of-the-mask",
      "score": 2
    },
    {
      "slug": "unpark-me",
      "score": 2
    },
    {
      "slug": "we-become-what-we-behold",
      "score": 2
    },
    {
      "slug": "2020-connect",
      "score": 1
    },
    {
      "slug": "2048-pizza",
      "score": 1
    },
    {
      "slug": "3-tricky-quests",
      "score": 1
    },
    {
      "slug": "4-in-row-mania",
      "score": 1
    },
    {
      "slug": "alien-hominid",
      "score": 1
    },
    {
      "slug": "armored-assault-strike",
      "score": 1
    },
    {
      "slug": "backyard-zombie-defense",
      "score": 1
    },
    {
      "slug": "bad-ice-cream",
      "score": 1
    },
    {
      "slug": "bad-ice-cream-2",
      "score": 1
    },
    {
      "slug": "basket-battle",
      "score": 1
    },
    {
      "slug": "bejeweled",
      "score": 1
    },
    {
      "slug": "bloons-td",
      "score": 1
    },
    {
      "slug": "bloons-td-4",
      "score": 1
    },
    {
      "slug": "bowling-stars",
      "score": 1
    },
    {
      "slug": "brain-trainer",
      "score": 1
    },
    {
      "slug": "bridge",
      "score": 1
    },
    {
      "slug": "bubble-shooter-hd",
      "score": 1
    },
    {
      "slug": "butterfly-shimai",
      "score": 1
    },
    {
      "slug": "carrom-challenges",
      "score": 1
    },
    {
      "slug": "clash-of-warriors",
      "score": 1
    },
    {
      "slug": "collect-same-thing",
      "score": 1
    },
    {
      "slug": "color-burst-3d",
      "score": 1
    },
    {
      "slug": "color-jump",
      "score": 1
    },
    {
      "slug": "confront",
      "score": 1
    },
    {
      "slug": "cooking-mama",
      "score": 1
    },
    {
      "slug": "cooking-mania",
      "score": 1
    },
    {
      "slug": "crash-bandicoot",
      "score": 1
    },
    {
      "slug": "crazy-cars",
      "score": 1
    },
    {
      "slug": "crazy-caves",
      "score": 1
    },
    {
      "slug": "cube-tower",
      "score": 1
    },
    {
      "slug": "daily-room-escape",
      "score": 1
    },
    {
      "slug": "dandyrunki-retake",
      "score": 1
    },
    {
      "slug": "dogeminer",
      "score": 1
    },
    {
      "slug": "domino-adventure",
      "score": 1
    },
    {
      "slug": "doodle-jump",
      "score": 1
    },
    {
      "slug": "ducklings",
      "score": 1
    },
    {
      "slug": "fancy-pants-2",
      "score": 1
    },
    {
      "slug": "fullspeed-racing",
      "score": 1
    },
    {
      "slug": "g-switch-4",
      "score": 1
    },
    {
      "slug": "geometry-dash-world",
      "score": 1
    },
    {
      "slug": "go-escape",
      "score": 1
    },
    {
      "slug": "going-balls",
      "score": 1
    },
    {
      "slug": "gold-miner",
      "score": 1
    },
    {
      "slug": "golf-fling",
      "score": 1
    },
    {
      "slug": "granny-hero",
      "score": 1
    },
    {
      "slug": "hex-puzzle",
      "score": 1
    },
    {
      "slug": "hole-io",
      "score": 1
    },
    {
      "slug": "hoop-stars",
      "score": 1
    },
    {
      "slug": "house-flip",
      "score": 1
    },
    {
      "slug": "idle-restaurants",
      "score": 1
    },
    {
      "slug": "incredibox-shatter-sprunk",
      "score": 1
    },
    {
      "slug": "jetpack-joyride",
      "score": 1
    },
    {
      "slug": "learn-to-fly",
      "score": 1
    },
    {
      "slug": "light-line",
      "score": 1
    },
    {
      "slug": "love-tester",
      "score": 1
    },
    {
      "slug": "mahjong-3d",
      "score": 1
    },
    {
      "slug": "merge-defenders",
      "score": 1
    },
    {
      "slug": "merge-fruit",
      "score": 1
    },
    {
      "slug": "minecraft-cave-escape",
      "score": 1
    },
    {
      "slug": "mini-crossword",
      "score": 1
    },
    {
      "slug": "monopoly",
      "score": 1
    },
    {
      "slug": "nature-strikes-back",
      "score": 1
    },
    {
      "slug": "neon-rider",
      "score": 1
    },
    {
      "slug": "neon-tower",
      "score": 1
    },
    {
      "slug": "pocket-battle-royale",
      "score": 1
    },
    {
      "slug": "pocket-champions",
      "score": 1
    },
    {
      "slug": "pou",
      "score": 1
    },
    {
      "slug": "raft-wars",
      "score": 1
    },
    {
      "slug": "rampage-road",
      "score": 1
    },
    {
      "slug": "red-ball",
      "score": 1
    },
    {
      "slug": "roll-this-ball-3",
      "score": 1
    },
    {
      "slug": "sky-tower",
      "score": 1
    },
    {
      "slug": "slither-io",
      "score": 1
    },
    {
      "slug": "solitaire",
      "score": 1
    },
    {
      "slug": "spacebar-clicker",
      "score": 1
    },
    {
      "slug": "speed-master",
      "score": 1
    },
    {
      "slug": "sprunki-but-with-memes",
      "score": 1
    },
    {
      "slug": "sprunki-interactive-beta",
      "score": 1
    },
    {
      "slug": "sprunki-like-minecraft",
      "score": 1
    },
    {
      "slug": "sprunki-maker",
      "score": 1
    },
    {
      "slug": "sprunki-minecraft",
      "score": 1
    },
    {
      "slug": "sprunki-night-time",
      "score": 1
    },
    {
      "slug": "sprunki-play-random",
      "score": 1
    },
    {
      "slug": "sprunki-police-and-prisoners",
      "score": 1
    },
    {
      "slug": "stars-aligned",
      "score": 1
    },
    {
      "slug": "stealing-the-diamond",
      "score": 1
    },
    {
      "slug": "super-bowling-mania",
      "score": 1
    },
    {
      "slug": "swap-sprunkgerny",
      "score": 1
    },
    {
      "slug": "tank-trouble",
      "score": 1
    },
    {
      "slug": "tiger-run",
      "score": 1
    },
    {
      "slug": "totemia-cursed-marbles",
      "score": 1
    },
    {
      "slug": "tractor-mania",
      "score": 1
    },
    {
      "slug": "uno",
      "score": 1
    },
    {
      "slug": "word-connect",
      "score": 1
    },
    {
      "slug": "word-pics",
      "score": 1
    },
    {
      "slug": "words-challenge",
      "score": 1
    },
    {
      "slug": "yohoho-io",
      "score": 1
    },
    {
      "slug": "zombie-ragdoll",
      "score": 1
    }
  ]
}
